sam_url_cache/__init__.py
sam_url_cache/cache.py
sam_url_cache/url.py
sam_url_cache-0.7.dist-info/METADATA
sam_url_cache-0.7.dist-info/WHEEL
sam_url_cache-0.7.dist-info/top_level.txt
sam_url_cache-0.7.dist-info/RECORD
