Metadata-Version: 2.1
Name: sam_url_cache
Version: 0.7
Summary: A simple URL caching library for Python
Author: Sam Pomerantz
Author-email: sam@sampomerantz.me
Project-URL: Source, https://github.com/SamPom100/sam-url-cache
Project-URL: Portfolio, https://sampomerantz.me
Requires-Dist: requests
